{
  "generatedAt": "2026-07-18T19:55:57.287Z",
  "baseRef": "HEAD^",
  "baseStatus": "git-ref",
  "baseWarning": null,
  "current": "working tree",
  "sourceOfTruth": {
    "widgetbook": "widgetbook/lib/main.directories.g.dart",
    "catalog": "docs/widget_catalog.md",
    "policy": "New public widget classes need Widgetbook and widget catalog coverage. New private widget classes and Widget-returning helpers must be inlined/deleted, merged into an existing primitive, or promoted to public cataloged widgets."
  },
  "summary": {
    "addedWidgetClasses": 1,
    "addedPublicWidgetClasses": 1,
    "addedPrivateWidgetClasses": 0,
    "addedWidgetReturningHelpers": 0,
    "movedWidgetClasses": 0,
    "movedWidgetReturningHelpers": 0,
    "coveredNewWidgets": 1,
    "unresolved": 0,
    "widgetsByStatus": {
      "covered": 1
    },
    "helpersByStatus": {},
    "issues": {}
  },
  "movedWidgets": [],
  "movedWidgetHelpers": [],
  "addedWidgets": [
    {
      "name": "ChatBlastComposerSheet",
      "baseClass": "StatelessWidget",
      "visibility": "public",
      "line": 10,
      "file": "lib/chats/presentation/inbox/chat_blast_composer_sheet.dart",
      "library": "lib/chats/presentation/inbox/chat_blast_composer_sheet.dart",
      "widgetbookCovered": true,
      "catalogMentioned": true,
      "status": "covered",
      "issues": [],
      "recommendedAction": "Covered by Widgetbook and docs/widget_catalog.md."
    }
  ],
  "addedWidgetHelpers": []
}
