{
  "actions": [
    {
      "entityId": "afterfly",
      "merge": false,
      "path": "clubs/afterfly",
      "reason": "missing_claim_target",
      "requiresFirestoreDryRun": true,
      "status": "create",
      "writeFieldCount": 42,
      "writeFields": [
        "appVisibility",
        "archiveReason",
        "archived",
        "archivedAt",
        "area",
        "cityName",
        "claim",
        "countryCode",
        "countryName",
        "createdAt",
        "description",
        "displayCategory",
        "email",
        "entityKind",
        "entitySubtypes",
        "hostAvatarUrl",
        "hostDefaults",
        "hostName",
        "hostProfiles",
        "hostUserId",
        "hostUserIds",
        "imageUrl",
        "instagramHandle",
        "location",
        "memberCount",
        "name",
        "nextEventAt",
        "nextEventLabel",
        "ownerUserId",
        "ownership",
        "phoneNumber",
        "profileImageUrl",
        "provenance",
        "publicPage",
        "publicProfile",
        "publicSources",
        "rating",
        "regionName",
        "reviewCount",
        "status",
        "tags",
        "verifiedReviewCount"
      ],
      "writesRemoteData": true
    },
    {
      "entityId": "bhag",
      "merge": false,
      "path": "clubs/bhag",
      "reason": "missing_claim_target",
      "requiresFirestoreDryRun": true,
      "status": "create",
      "writeFieldCount": 42,
      "writeFields": [
        "appVisibility",
        "archiveReason",
        "archived",
        "archivedAt",
        "area",
        "cityName",
        "claim",
        "countryCode",
        "countryName",
        "createdAt",
        "description",
        "displayCategory",
        "email",
        "entityKind",
        "entitySubtypes",
        "hostAvatarUrl",
        "hostDefaults",
        "hostName",
        "hostProfiles",
        "hostUserId",
        "hostUserIds",
        "imageUrl",
        "instagramHandle",
        "location",
        "memberCount",
        "name",
        "nextEventAt",
        "nextEventLabel",
        "ownerUserId",
        "ownership",
        "phoneNumber",
        "profileImageUrl",
        "provenance",
        "publicPage",
        "publicProfile",
        "publicSources",
        "rating",
        "regionName",
        "reviewCount",
        "status",
        "tags",
        "verifiedReviewCount"
      ],
      "writesRemoteData": true
    }
  ],
  "commands": {
    "firestoreDryRun": "node tool/organizer_intake/sync_claim_targets_to_firestore.mjs --env dev",
    "firestoreWrite": "node tool/organizer_intake/sync_claim_targets_to_firestore.mjs --env dev --write",
    "localFixturePreview": "node tool/organizer_intake/sync_claim_targets_to_firestore.mjs --fixture tool/organizer_intake/fixtures/existing_club_docs.empty.json"
  },
  "generatedFrom": {
    "claimTargetPlan": "tool/organizer_intake/generated/organizer_claim_targets.json",
    "existingDocsSource": "tool/organizer_intake/fixtures/existing_club_docs.empty.json"
  },
  "guardrails": [
    "This preview never reads or writes Firestore.",
    "Before any remote write, run sync_claim_targets_to_firestore.mjs without --write against the target Firebase project.",
    "Owner-bound club documents must be skipped, never overwritten.",
    "Refresh actions may update public fields only; ownership, claim, and aggregate fields stay server-owned."
  ],
  "mode": {
    "assumesMissingWhenNotInFixture": true,
    "existingDocsSource": "tool/organizer_intake/fixtures/existing_club_docs.empty.json",
    "previewOnly": true,
    "remoteReads": 0,
    "remoteWrites": 0
  },
  "schemaVersion": 1,
  "summary": {
    "creates": 2,
    "inSync": 0,
    "refreshes": 0,
    "skippedOwnerBound": 0,
    "targets": 2,
    "writesNeeded": 2
  }
}
